deepbays/__init__.py
deepbays/main.py
deepbays/NN/__init__.py
deepbays/NN/networks.py
deepbays/NN/training.py
deepbays/kernels/__init__.py
deepbays/kernels/kernels.py
deepbays/kernels/kernels_cuda.py
deepbays/kernels/kernels_torch.py
deepbays/rkgp/__init__.py
deepbays/rkgp/theory_1HL_CONV.py
deepbays/rkgp/theory_1HL_FC_multiple_output.py
deepbays/rkgp/theory_1HL_FC_single_output.py
deepbays/rkgp/theory_1HL_FC_single_output_cuda.py
deepbays/rkgp/theory_1HL_extras.py
deepbays/rkgp/theory_deep_FC.py
deepbays/tasks/__init__.py
deepbays/tasks/classic_tasks.py
deepbays/tasks/extra_tasks.py
deepbays/tasks/synthetic_tasks.py
deepbays-0.1.11.dist-info/LICENSE
deepbays-0.1.11.dist-info/METADATA
deepbays-0.1.11.dist-info/WHEEL
deepbays-0.1.11.dist-info/top_level.txt
deepbays-0.1.11.dist-info/RECORD
