Metadata-Version: 2.1
Name: deepbays
Version: 0.1.11
Summary: Bayesian deep neural networks in the proportional regime as renormalized kernel gaussian processes
Author: Rosalba Pacelli
Author-email: <rosalba.pacelli@gmail.com>
Keywords: python,machine learning,gaussian processes,neural networks
License-File: LICENSE
Requires-Dist: numpy
Requires-Dist: torch
Requires-Dist: torchvision
Requires-Dist: scipy
